HDL Castillo/Experiment1/Experiment 1/drill1_1.v
//Castillo, Joaquin Iverson M.
//2020759

module circuit1_1(A,B,C,X);
     input      A,B,C;
     output     X;
     wire       wire1,wire2,wire3;

     not        NOT(wire2,A);
     xor        EOR(wire1,B,C);
     and        AND2(wire3,wire1,A);
     nor        NOR2(X,wire3,wire2);
endmodule

module testbench1_1; 

     reg        A,B,C;
     wire       Z;
     circuit1_1 tb1(A,B,C,Z);
     initial
     begin 
             A=1'b0;B=1'b0;C=1'b0;
             $display("Simulating output for circuit1_1");
             $monitor("A=%b B=%b C=%b Z=%b",A,B,C,Z);

             #2 A=1'b0; B=1'b0; C=1'b1;
             #1 A=1'b0; B=1'b1; C=1'b0;
             #1 A=1'b0; B=1'b1; C=1'b1;
             #1 A=1'b1; B=1'b0; C=1'b0;
             #1 A=1'b1; B=1'b0; C=1'b1;
             #1 A=1'b1; B=1'b1; C=1'b0;
             #1 A=1'b1; B=1'b1; C=1'b1;
             #2 $finish;
    end
endmodule

HDL Castillo/Experiment1/Experiment 1/drill1_1.vcd
$date
	Mon Oct 10 15:15:20 2022
$end
$version
	Icarus Verilog
$end
$timescale
	1s
$end
$scope module testbench1_1 $end
$scope module tb1 $end
$var wire 1 ! A $end
$var wire 1 " B $end
$var wire 1 # C $end
$var wire 1 $ X $end
$var wire 1 % wire1 $end
$var wire 1 & wire2 $end
$var wire 1 ' wire3 $end
$upscope $end
$upscope $end
$enddefinitions $end
$comment Show the parameter values. $end
$dumpall
$end
#0
$dumpvars
0'
1&
0%
0$
0#
0"
0!
$end
#10
1%
1#
#20
0#
1"
#30
0%
1#
#40
1$
0&
0#
0"
1!
#50
0$
1'
1%
1#
#60
0#
1"
#70
1$
0'
0%
1#
